djangorestframework_pagination/__init__.py
djangorestframework_pagination/pagination.py
djangorestframework_pagination-1.1.dist-info/LICENSE
djangorestframework_pagination-1.1.dist-info/METADATA
djangorestframework_pagination-1.1.dist-info/WHEEL
djangorestframework_pagination-1.1.dist-info/top_level.txt
djangorestframework_pagination-1.1.dist-info/RECORD
