Metadata-Version: 2.1
Name: djangorestframework_pagination
Version: 1.1
Summary: response pagination using django restframework
Home-page: https://github.com/alishekari/djangorestframework_pagination
Author: Ali Shekari
Author-email: alishekari1991@outlook.com
License: UNKNOWN
Project-URL: Bug Tracker, https://github.com/alishekari/djangorestframework_pagination/issues
Platform: UNKNOWN
Classifier: Programming Language :: Python :: 3.10
Classifier: License :: OSI Approved :: MIT License
Classifier: Operating System :: OS Independent
Requires-Python: >=3.0
License-File: LICENSE
